summator_bit1.v
module summator_bit1
#(parameter serial_number = 0)
( 
  // объявление входных портов или входов
  input wire input_number0, input_number1, 
  //input wire input_reset,
  input wire input_clk,
  //
  input wire input_write_enabled,  
  // объявление выходных портов или выходов
  
    
  output reg output_bit1, 
             output_bit2,
			 output_calculated
  ); 
  
 //объявление внутренней цепи, необходимой для работы
 // схемы и не являющейся входным/выходным портом
 wire bit1, bit0;  
 
 reg r_calculated;
 wire w_calculated;
 
 assign bit1 = (input_number0 & input_number1);
 assign bit0 = (!(input_number0 & input_number1)) & (input_number0 | input_number1);
 assign w_calculated = r_calculated; 
 
 always @ (posedge input_clk //or posedge input_reset
 )
 begin
	/*
	if (input_reset)
	    begin
	      output_bit1 <= 1'bX;
		  output_bit2 <= 1'bX;
		  r_calculated  <= 0;		  		    
		  
		  $display("Reset (summator 1 bit %d): %b %b", serial_number, output_bit1, output_bit2);
	    end
    else   */
	if(input_write_enabled)
        begin		
          output_bit1 <= bit1;
		  output_bit2 <= bit0;
		  
		  r_calculated <= 1;  
		  output_calculated <= w_calculated;  
		  
          $display("summator 1 bit %d: Writte enabled, input=%b%b, output=%b%b", serial_number , input_number0, input_number1, output_bit1, output_bit2);
        end
    else
        begin
		  //Рабочий цикл
		  //if (!w_calculated)
		  //    begin
		  //	    output_bit1 <= 1'bX;
		  //      output_bit2 <= 1'bX;
		  //	  end
			  
		  //output_calculated = w_calculated;  
		  output_bit1 <= 1'bX;
		  output_bit2 <= 1'bX;
		  r_calculated <= 0;  
		  output_calculated <= r_calculated;  		

		  //$display("Summ (summator 1 bit %d): %b %b", serial_number ,output_bit1, output_bit2);
		end 
end

endmodule

summator_bit1_test.v
 
 module summator_bit1_test;

wire number0, number1;

reg
// reset, 
clk, wr;

//Выходные данные
wire [1:0] w_data;
reg [1:0]wdata;
wire w_data_calculated;
reg data_calculated;

reg [1:0] counter;

//устанавливаем экземпляр тестируемого модуля
summator_bit1 #(.serial_number(123456789)) summator1bit ( 
  // объявление входных портов или входов
  .input_number0(number0), .input_number1(number1), 
  //.input_reset(reset),
  .input_clk(clk),
  //Разрешение подсчета
  .input_write_enabled(wr),  
  // объявление выходных портов или выходов
  
    
  .output_bit1(w_data[1]), 
  .output_bit2(w_data[0]),
  .output_calculated(w_data_calculated)
  ); 
  
assign number0 = counter[0];
assign number1 = counter[1];

//моделируем сигнал тактовой частоты
always
  #10 begin
      clk = ~clk;
  
      if (wr == 1'b0)
	  begin
	   if (counter == 2'b00) 
	     counter <= 2'b01;
       else if (counter == 2'b01) 
	     counter <= 2'b10;
       else if (counter == 2'b10) 
	     counter <= 2'b11;
	   else if (counter == 2'b11) 
	     counter <= 2'b00;
       else  
	     counter <= 2'b00;
	   
	   wr <= 1'b1;	
	  end
	  
	  if (w_data_calculated == 0)
	    begin
	      $display("summator_bit1_test (%d): %d", summator1bit.serial_number , w_data);
	      wdata <= w_data;
	      if (wr == 1'b1)
          wr <= 1'b0;	  
        end	 
	 end
/*
always @(posedge w_data_calculated)
  begin
	   $display("summator_bit1_test (%d): %d", summator1bit.serial_number , w_data);
	   wdata <= w_data;
	   if (wr == 1'b1)
         wr <= 1'b0;	  
    end	 
	*/
//от начала времени...

initial
begin
  clk = 0;
  //reset = 0;
  wr = 1'b0;
  counter = 2'b00;
  
//через временной интервал "50" подаем сигнал сброса
  //#50 reset = 1;

//еще через время "4" снимаем сигнал сброса

  //#10 reset = 0;

//пауза длительностью "50"
  #50;

//ждем фронта тактовой частоты и сразу после нее подаем сигнал записи
  @(posedge clk)
  #0
    begin 	  
      //wr = 1'b1;
    end

//по следующему фронту снимаем сигнал записи
  @(posedge clk)
  #0
    begin
      //wr = 1'b0;
    end
 /*
  @(posedge data_calculated)
  #0
    begin
	   $display("Summator (1 bit %d): %d", summator1bit.serial_number , w_data);
	   wdata <= w_data;
      //wr = 1'b0;
	  
    end
  */
  
end

//заканчиваем симуляцию в момент времени "400"
initial
begin
  #400 $finish;
end

//создаем файл VCD для последующего анализа сигналов
initial
begin
  $dumpfile("out.vcd");
  $dumpvars(0,summator_bit1_test);
end

//наблюдаем на некоторыми сигналами системы
initial
$monitor($stime,, clk,,, number0, number1,, wdata,, wr,, w_data_calculated);

endmodule

out.vcd
$date
	Sun May 14 17:05:31 2023
$end
$version
	Icarus Verilog
$end
$timescale
	1s
$end
$scope module summator_bit1_test $end
$var wire 1 ! w_data_calculated $end
$var wire 2 " w_data [1:0] $end
$var wire 1 # number1 $end
$var wire 1 $ number0 $end
$var reg 1 % clk $end
$var reg 2 & counter [1:0] $end
$var reg 2 ' wdata [1:0] $end
$var reg 1 ( wr $end
$scope module summator1bit $end
$var wire 1 ) bit0 $end
$var wire 1 * bit1 $end
$var wire 1 % input_clk $end
$var wire 1 $ input_number0 $end
$var wire 1 # input_number1 $end
$var wire 1 ( input_write_enabled $end
$var wire 1 + w_calculated $end
$var reg 1 , output_bit1 $end
$var reg 1 - output_bit2 $end
$var reg 1 ! output_calculated $end
$var reg 1 . r_calculated $end
$upscope $end
$upscope $end
$enddefinitions $end
#0
$dumpvars
x.
x-
x,
x+
0*
0)
0(
bx '
b0 &
0%
0$
0#
bx "
x!
$end
#10
1)
1$
0+
0.
1(
b1 &
1%
#20
0%
#30
0!
1+
1.
1-
b1 "
0,
1%
#40
0(
b1 '
0%
#50
0$
1#
1!
0+
0.
x-
bx "
x,
1(
b10 &
1%
#60
0%
#70
0!
1+
1.
1-
b1 "
0,
1%
#80
0(
0%
#90
0)
1*
1$
1!
0+
0.
x-
bx "
x,
1(
b11 &
1%
#100
0%
#110
0!
1+
1.
0-
b10 "
1,
1%
#120
0(
b10 '
0%
#130
0*
0$
0#
1!
0+
0.
x-
bx "
x,
1(
b0 &
1%
#140
0%
#150
0!
1+
1.
0-
b0 "
0,
1%
#160
0(
b0 '
0%
#170
1)
1$
1!
0+
0.
x-
bx "
x,
1(
b1 &
1%
#180
0%
#190
0!
1+
1.
1-
b1 "
0,
1%
#200
0(
b1 '
0%
#210
0$
1#
1!
0+
0.
x-
bx "
x,
1(
b10 &
1%
#220
0%
#230
0!
1+
1.
1-
b1 "
0,
1%
#240
0(
0%
#250
0)
1*
1$
1!
0+
0.
x-
bx "
x,
1(
b11 &
1%
#260
0%
#270
0!
1+
1.
0-
b10 "
1,
1%
#280
0(
b10 '
0%
#290
0*
0$
0#
1!
0+
0.
x-
bx "
x,
1(
b0 &
1%
#300
0%
#310
0!
1+
1.
0-
b0 "
0,
1%
#320
0(
b0 '
0%
#330
1)
1$
1!
0+
0.
x-
bx "
x,
1(
b1 &
1%
#340
0%
#350
0!
1+
1.
1-
b1 "
0,
1%
#360
0(
b1 '
0%
#370
0$
1#
1!
0+
0.
x-
bx "
x,
1(
b10 &
1%
#380
0%
#390
0!
1+
1.
1-
b1 "
0,
1%
